ihelper/__init__.py
ihelper/__main__.py
ihelper/assets/__init__.py
ihelper/assets/avatar.py
ihelper/assets/favicon.py
ihelper/assets/main.py
ihelper/assets/typing.py
ihelper/git/__init__.py
ihelper/git/main.py
ihelper/git/secret/__init__.py
ihelper/git/secret/delete/__init__.py
ihelper/git/secret/delete/main.py
ihelper/git/secret/delete/pypi.py
ihelper/git/secret/main.py
ihelper/git/secret/set/__init__.py
ihelper/git/secret/set/main.py
ihelper/git/secret/set/pypi.py
ihelper/git/secret/utils.py
ihelper/key/__init__.py
ihelper/key/_import/__init__.py
ihelper/key/_import/gpg.py
ihelper/key/_import/main.py
ihelper/key/_import/ssh.py
ihelper/key/export/__init__.py
ihelper/key/export/gpg.py
ihelper/key/export/main.py
ihelper/key/export/ssh.py
ihelper/key/main.py
ihelper/key/typing.py
ihelper/update/__init__.py
ihelper/update/apt.py
ihelper/update/brew.py
ihelper/update/ignore_io.py
ihelper/update/main.py
ihelper/update/snap.py
ihelper/update/tldr.py
ihelper-0.1.2.dist-info/METADATA
ihelper-0.1.2.dist-info/WHEEL
ihelper-0.1.2.dist-info/LICENSE
ihelper-0.1.2.dist-info/RECORD
