Metadata-Version: 2.1
Name: ihelper
Version: 0.1.2
Summary: My Helpers
Home-page: https://github.com/liblaf/ihelper
License: MIT
Author: Qin Li
Author-email: liblaf@outlook.com
Requires-Python: >=3.11,<3.12
Classifier: License :: OSI Approved :: MIT License
Classifier: Programming Language :: Python :: 3
Classifier: Programming Language :: Python :: 3.11
Requires-Dist: click (>=8.1.3,<9.0.0)
Requires-Dist: ishutils (>=0.1.2,<0.2.0)
Requires-Dist: python-slugify (>=7.0.0,<8.0.0)
Project-URL: Repository, https://github.com/liblaf/ihelper
